ipitin/__init__.py
ipitin/ipitin.py
ipitin/menual.py
ipitin-0.0.3.dist-info/LICENSE
ipitin-0.0.3.dist-info/METADATA
ipitin-0.0.3.dist-info/WHEEL
ipitin-0.0.3.dist-info/top_level.txt
ipitin-0.0.3.dist-info/RECORD
